{
  "schemaVersion": 1,
  "generatedBy": "scripts/generate-rule-index.mjs",
  "rules": [
    {
      "path": ".ai/rules/architecture/03-auth-rbac.mdc",
      "description": "项目统一的 RBAC 权限控制标准（Vue 模板指令与 TSX 编程式鉴权）。",
      "globs": ["**/*.vue", "**/*.tsx"],
      "alwaysApply": false
    },
    {
      "path": ".ai/rules/architecture/04-store-organization.mdc",
      "description": "Pinia store grouping contract for system/session/ui ownership and backwards-compatible import surfaces.",
      "globs": ["src/stores/**/*.ts", "src/**/*.ts", "src/**/*.vue", "src/**/*.tsx"],
      "alwaysApply": false
    },
    {
      "path": ".ai/rules/architecture/05-runtime-bootstrap.mdc",
      "description": "Runtime bootstrap contract for index.html first-paint scripts, preload cache keys, and startup handoff consistency.",
      "globs": [
        "index.html",
        "build/**/*.ts",
        "src/main.ts",
        "src/constants/**/*.ts",
        "src/utils/theme/**/*.ts",
        "src/stores/**/*.ts"
      ],
      "alwaysApply": false
    },
    {
      "path": ".ai/rules/components/00-primevue-ecosystem.mdc",
      "description": "PrimeVue v4 Ecosystem — Component Substitution Law, API Zero-Hallucination Protocol, and PT Styling Mandate. Read BEFORE using any interactive or data UI element.",
      "globs": [
        "src/components/**/*.{vue,tsx}",
        "src/views/**/*.{vue,tsx}",
        "src/layouts/**/*.{vue,tsx}"
      ],
      "alwaysApply": true
    },
    {
      "path": ".ai/rules/components/01-primevue-pt-styling.mdc",
      "description": "Unified PrimeVue PT styling law. Restores full PT architecture, whitelist/blacklist constraints, slot maps, and practical examples.",
      "globs": ["src/components/**/*.vue", "src/views/**/*.vue"],
      "alwaysApply": true
    },
    {
      "path": ".ai/rules/components/02-pro-components.mdc",
      "description": "Governs all business views and ProTable/ProForm usage. Enforces PrimeVue purity, semantic layout shell, v-auth directive, and responsive patterns.",
      "globs": [
        "src/views/**/*.vue",
        "src/views/**/*.tsx",
        "src/components/ProTable/**",
        "src/components/ProForm/**"
      ],
      "alwaysApply": true
    },
    {
      "path": ".ai/rules/components/03-echarts-theming.mdc",
      "description": "Enforces the useChartTheme wrapper for ECharts to ensure dark mode and theme color reactivity.",
      "globs": [
        "src/components/**/*.vue",
        "src/components/UseEcharts/**/*.ts",
        "src/views/**/*.vue"
      ],
      "alwaysApply": true
    },
    {
      "path": ".ai/rules/core/00-global-architect.mdc",
      "description": "Chief Architect Global Directives, Ledger tracking, and fundamental workflow constraints. Applies to all files and operations.",
      "globs": ["**/*"],
      "alwaysApply": false
    },
    {
      "path": ".ai/rules/core/00-root-gatekeeper.mdc",
      "description": "Root gatekeeper for rules lookup and tool/hook priority.",
      "globs": ["*"],
      "alwaysApply": true
    },
    {
      "path": ".ai/rules/core/01-global-preflight.mdc",
      "description": "MANDATORY global pre-execution architect checklist for protocol, logic, and cross-layer safety checks.",
      "globs": ["**/*"],
      "alwaysApply": true
    },
    {
      "path": ".ai/rules/core/02-core-engineering.mdc",
      "description": "Core engineering constitution for Vue3+TS architecture, type safety, rendering, and build/runtime boundaries.",
      "globs": ["**/*.vue", "**/*.ts", "**/*.tsx", "**/*.js"],
      "alwaysApply": false
    },
    {
      "path": ".ai/rules/core/02-ui-preflight.mdc",
      "description": "MANDATORY UI pre-execution architect checklist for views, components, layouts, and design-engine constraints.",
      "globs": ["src/views/**/*", "src/components/**/*", "src/layouts/**/*"],
      "alwaysApply": true
    },
    {
      "path": ".ai/rules/core/03-vue3-ts-architecture.mdc",
      "description": "Vue 3 Composition API Architecture — script setup macro discipline, reactivity primitives, typed component contracts, composable design axioms, performance patterns.",
      "globs": ["src/**/*.vue", "src/**/*.ts", "src/**/*.tsx"],
      "alwaysApply": true
    },
    {
      "path": ".ai/rules/core/04-type-safety-mutations.mdc",
      "description": "Bans type assertions and in-place mutations in business logic. Mandates typeCasters.ts for casting and lodashes.ts for deep operations. Applies codebase-wide.",
      "globs": ["src/**/*.ts", "src/**/*.vue", "src/**/*.tsx"],
      "alwaysApply": false
    },
    {
      "path": ".ai/rules/core/05-state-boundaries.mdc",
      "description": "Enforces the API Call Isolation Law, Pinia store ownership matrix, and cross-layer data flow. Applies to all business logic in src/.",
      "globs": ["src/**/*.ts", "src/**/*.vue", "src/**/*.tsx"],
      "alwaysApply": false
    },
    {
      "path": ".ai/rules/core/06-utils-hooks.mdc",
      "description": "Enforces the Search Before Writing rule for utility hooks and global events.",
      "globs": ["src/**/*.vue", "src/**/*.ts"],
      "alwaysApply": true
    },
    {
      "path": ".ai/rules/core/07-vue-auto-imports.mdc",
      "description": "Canonical auto-import contract for this project. Defines exactly which APIs and components are globally available without import statements, and strictly forbids redundant manual imports.",
      "globs": ["src/**/*.vue", "src/**/*.ts", "src/**/*.tsx"],
      "alwaysApply": true
    },
    {
      "path": ".ai/rules/core/08-vue-template-strictness.mdc",
      "description": "Strict enforcement rules for Vue SFC template blocks and script setup type safety. Bans TypeScript syntax inside <template>, forbids any/unknown in component logic, and mandates computed-based type narrowing.",
      "globs": ["src/**/*.vue", "src/**/*.tsx"],
      "alwaysApply": true
    },
    {
      "path": ".ai/rules/core/09-ai-anti-failure-guard.mdc",
      "description": "CRITICAL AI Execution Guardrails. Prevents UnoCSS purge, Vue reactivity loss, Type deadlocks, and Intent erasure. Includes Self-Check Loop.",
      "globs": ["**/*.vue", "**/*.ts"],
      "alwaysApply": true
    },
    {
      "path": ".ai/rules/core/10-ai-generation-workflow.mdc",
      "description": "Enforces scaffold-first workflow for new routes/pages and hard validation for AI-generated business surfaces.",
      "globs": [
        "src/router/modules/**/*.ts",
        "src/views/**/*.vue",
        "src/hooks/modules/**/*.ts",
        ".ai/protocol/**/*.md",
        "scripts/**/*.mjs"
      ],
      "alwaysApply": true
    },
    {
      "path": ".ai/rules/design-system/00-unocss-guardrails.mdc",
      "description": "CRITICAL — Unified anti-hallucination and design-engine UnoCSS law. Contains closed shortcut registry, N-1/N-2/N-5 anti-patterns, unit/size/color/z-index constraints, and pre-output self-check.",
      "globs": [
        "**/*.vue",
        "**/*.tsx",
        "**/*.ts",
        "**/*.css",
        "**/*.scss",
        "**/uno.config.ts",
        "**/semanticShortcuts.ts"
      ],
      "alwaysApply": true
    },
    {
      "path": ".ai/rules/design-system/01-design-tokens.mdc",
      "description": "Enforces strict usage of Semantic Colors and Size variables (Design Tokens). Forbids magic numbers and hardcoded colors.",
      "globs": ["src/**/*.{vue,tsx,ts,css,scss}"],
      "alwaysApply": false
    },
    {
      "path": ".ai/rules/design-system/02-size-density-system.mdc",
      "description": "Enforces the Size Density System — correct usage of SIZE_PRESETS, CSS variable pipeline, and useSizeStore. Forbids hardcoded layout pixel values.",
      "globs": ["src/**/*.{vue,tsx,ts,css}"],
      "alwaysApply": true
    },
    {
      "path": ".ai/rules/design-system/03-material-system.mdc",
      "description": "Enforces Material System, Z-Index tokens, Motion curves, and strict Performance Guards for glassmorphism.",
      "globs": ["src/**/*.vue", "src/**/*.tsx", "src/**/*.ts"],
      "alwaysApply": true
    },
    {
      "path": ".ai/rules/design-system/04-design-state-contract.mdc",
      "description": "Enforces the UIDesignState AI Design Contract for every new page. All page-level structural and visual decisions MUST be anchored to this read-only contract before writing any code.",
      "globs": ["src/views/**/*.{vue,tsx,ts}"],
      "alwaysApply": true
    },
    {
      "path": ".ai/rules/design-system/05-semantic-color-usage-contract.mdc",
      "description": "AI semantic color contract for theme system and UnoCSS field usage",
      "globs": ["src/**/*.{vue,tsx,ts,css,scss}", ".ai/rules/**/*.mdc"],
      "alwaysApply": false
    },
    {
      "path": ".ai/rules/integrations/00-network-routing-guardrails.mdc",
      "description": "CRITICAL — Cross-concern anti-hallucination guardrails for HTTP networking (Alova) and Vue Router layers. Covers error handling responsibility split, DTO type-safety, navigation safety, connection awareness, and file operations.",
      "globs": [
        "src/api/**/*.ts",
        "src/hooks/**/*.ts",
        "src/views/**/*.vue",
        "src/router/**/*.ts",
        "src/stores/**/*.ts",
        "src/infra/**/*.ts"
      ],
      "alwaysApply": true
    },
    {
      "path": ".ai/rules/integrations/01-http-alova.mdc",
      "description": "Enforces Alova + useHttpRequest for all network calls. Restores full 401 responsibility boundaries, API structure constraints, and detailed error contract.",
      "globs": ["src/api/**/*.ts", "src/views/**/*.vue", "src/hooks/**/*.ts"],
      "alwaysApply": true
    },
    {
      "path": ".ai/rules/integrations/02-router-rbac.mdc",
      "description": "Enforces DynamicRouteManager and RBAC contract. Restores complete transformation chain and full AppRouteMeta reference.",
      "globs": ["src/router/**/*.ts", "src/views/**/*.vue"],
      "alwaysApply": true
    },
    {
      "path": ".ai/rules/integrations/03-layout-architecture.mdc",
      "description": "Unified layout runtime SSOT and responsive shell rendering rules.",
      "globs": ["src/layouts/**/*.{vue,tsx}", "src/App.vue"],
      "alwaysApply": true
    },
    {
      "path": ".ai/rules/integrations/04-safe-storage.mdc",
      "description": "Bans all native browser storage APIs for business data. Mandates AES+LZ-String encrypted wrappers from @/utils/safeStorage and createPiniaEncryptedSerializer for Pinia persistence.",
      "globs": ["src/**/*.ts", "src/**/*.vue", "src/**/*.tsx"],
      "alwaysApply": false
    },
    {
      "path": ".ai/rules/integrations/05-date-time.mdc",
      "description": "Bans native Date instantiation and forces useDateUtils/DateUtils. Restores full native ban list, initialization guard examples, and rationale.",
      "globs": ["src/**/*.ts", "src/**/*.vue", "src/**/*.tsx"],
      "alwaysApply": true
    },
    {
      "path": ".ai/rules/integrations/06-adapters-infra.mdc",
      "description": "Enforces the architectural boundaries for Adapters (Anti-Corruption Layer), Infra (Dependency Injection), and Types taxonomy.",
      "globs": ["src/adapters/**/*.ts", "src/infra/**/*.ts", "src/types/**/*.ts", "src/**/*.ts"],
      "alwaysApply": true
    },
    {
      "path": ".ai/rules/integrations/07-interaction-patterns.mdc",
      "description": "Cross-platform interaction patterns — touch/pointer event handling, hover boundary, gesture composables, and PrimeVue touch workarounds.",
      "globs": ["src/**/*.vue", "src/**/*.tsx", "src/**/*.ts"],
      "alwaysApply": true
    },
    {
      "path": ".ai/rules/integrations/08-cross-platform-tauri.mdc",
      "description": "Vite + Tauri v2 双端桥接规则，强制 OS 能力采用 isTauri 双分支与 Web fallback。",
      "globs": ["src/**/*.vue", "src/**/*.ts", "src/**/*.tsx"],
      "alwaysApply": false
    },
    {
      "path": ".ai/rules/integrations/08-playwright-visual-regression.mdc",
      "description": "Visual regression stability contract for Playwright first-paint, runtime loading, and theme-switch flows.",
      "globs": [
        "index.html",
        "build/**/*.ts",
        "playwright.config.ts",
        "e2e/**/*.ts",
        "src/**/*.{vue,ts,tsx}"
      ],
      "alwaysApply": false
    },
    {
      "path": ".ai/rules/integrations/09-desktop-branch-governance.mdc",
      "description": "Desktop branch governance for Vue 3 + Tauri v2 bridge, capability drift control, and snapshot hygiene.",
      "globs": [
        "src/**/*.ts",
        "src/**/*.vue",
        "src-tauri/**",
        "scripts/drift-check.mjs",
        "scripts/sync-desktop-config.mjs",
        "e2e/**",
        "test-results/**"
      ],
      "alwaysApply": false
    },
    {
      "path": ".ai/rules/integrations/10-desktop-preflight.mdc",
      "description": "MANDATORY Tauri desktop preflight checklist for runtime security, capability minimization, frameless drag safety, and release metadata alignment.",
      "globs": [
        "src-tauri/**",
        "src/utils/desktopWindow.ts",
        "src/utils/env.ts",
        "src/main.ts",
        "index.html",
        "package.json"
      ],
      "alwaysApply": true
    }
  ],
  "byGlob": {
    ".ai/protocol/**/*.md": [".ai/rules/core/10-ai-generation-workflow.mdc"],
    ".ai/rules/**/*.mdc": [".ai/rules/design-system/05-semantic-color-usage-contract.mdc"],
    "*": [".ai/rules/core/00-root-gatekeeper.mdc"],
    "**/*": [".ai/rules/core/00-global-architect.mdc", ".ai/rules/core/01-global-preflight.mdc"],
    "**/*.css": [".ai/rules/design-system/00-unocss-guardrails.mdc"],
    "**/*.js": [".ai/rules/core/02-core-engineering.mdc"],
    "**/*.scss": [".ai/rules/design-system/00-unocss-guardrails.mdc"],
    "**/*.ts": [
      ".ai/rules/core/02-core-engineering.mdc",
      ".ai/rules/core/09-ai-anti-failure-guard.mdc",
      ".ai/rules/design-system/00-unocss-guardrails.mdc"
    ],
    "**/*.tsx": [
      ".ai/rules/architecture/03-auth-rbac.mdc",
      ".ai/rules/core/02-core-engineering.mdc",
      ".ai/rules/design-system/00-unocss-guardrails.mdc"
    ],
    "**/*.vue": [
      ".ai/rules/architecture/03-auth-rbac.mdc",
      ".ai/rules/core/02-core-engineering.mdc",
      ".ai/rules/core/09-ai-anti-failure-guard.mdc",
      ".ai/rules/design-system/00-unocss-guardrails.mdc"
    ],
    "**/semanticShortcuts.ts": [".ai/rules/design-system/00-unocss-guardrails.mdc"],
    "**/uno.config.ts": [".ai/rules/design-system/00-unocss-guardrails.mdc"],
    "build/**/*.ts": [
      ".ai/rules/architecture/05-runtime-bootstrap.mdc",
      ".ai/rules/integrations/08-playwright-visual-regression.mdc"
    ],
    "e2e/**": [".ai/rules/integrations/09-desktop-branch-governance.mdc"],
    "e2e/**/*.ts": [".ai/rules/integrations/08-playwright-visual-regression.mdc"],
    "index.html": [
      ".ai/rules/architecture/05-runtime-bootstrap.mdc",
      ".ai/rules/integrations/08-playwright-visual-regression.mdc",
      ".ai/rules/integrations/10-desktop-preflight.mdc"
    ],
    "package.json": [".ai/rules/integrations/10-desktop-preflight.mdc"],
    "playwright.config.ts": [".ai/rules/integrations/08-playwright-visual-regression.mdc"],
    "scripts/**/*.mjs": [".ai/rules/core/10-ai-generation-workflow.mdc"],
    "scripts/drift-check.mjs": [".ai/rules/integrations/09-desktop-branch-governance.mdc"],
    "scripts/sync-desktop-config.mjs": [".ai/rules/integrations/09-desktop-branch-governance.mdc"],
    "src-tauri/**": [
      ".ai/rules/integrations/09-desktop-branch-governance.mdc",
      ".ai/rules/integrations/10-desktop-preflight.mdc"
    ],
    "src/**/*.{vue,ts,tsx}": [".ai/rules/integrations/08-playwright-visual-regression.mdc"],
    "src/**/*.{vue,tsx,ts,css,scss}": [
      ".ai/rules/design-system/01-design-tokens.mdc",
      ".ai/rules/design-system/05-semantic-color-usage-contract.mdc"
    ],
    "src/**/*.{vue,tsx,ts,css}": [".ai/rules/design-system/02-size-density-system.mdc"],
    "src/**/*.ts": [
      ".ai/rules/architecture/04-store-organization.mdc",
      ".ai/rules/core/03-vue3-ts-architecture.mdc",
      ".ai/rules/core/04-type-safety-mutations.mdc",
      ".ai/rules/core/05-state-boundaries.mdc",
      ".ai/rules/core/06-utils-hooks.mdc",
      ".ai/rules/core/07-vue-auto-imports.mdc",
      ".ai/rules/design-system/03-material-system.mdc",
      ".ai/rules/integrations/04-safe-storage.mdc",
      ".ai/rules/integrations/05-date-time.mdc",
      ".ai/rules/integrations/06-adapters-infra.mdc",
      ".ai/rules/integrations/07-interaction-patterns.mdc",
      ".ai/rules/integrations/08-cross-platform-tauri.mdc",
      ".ai/rules/integrations/09-desktop-branch-governance.mdc"
    ],
    "src/**/*.tsx": [
      ".ai/rules/architecture/04-store-organization.mdc",
      ".ai/rules/core/03-vue3-ts-architecture.mdc",
      ".ai/rules/core/04-type-safety-mutations.mdc",
      ".ai/rules/core/05-state-boundaries.mdc",
      ".ai/rules/core/07-vue-auto-imports.mdc",
      ".ai/rules/core/08-vue-template-strictness.mdc",
      ".ai/rules/design-system/03-material-system.mdc",
      ".ai/rules/integrations/04-safe-storage.mdc",
      ".ai/rules/integrations/05-date-time.mdc",
      ".ai/rules/integrations/07-interaction-patterns.mdc",
      ".ai/rules/integrations/08-cross-platform-tauri.mdc"
    ],
    "src/**/*.vue": [
      ".ai/rules/architecture/04-store-organization.mdc",
      ".ai/rules/core/03-vue3-ts-architecture.mdc",
      ".ai/rules/core/04-type-safety-mutations.mdc",
      ".ai/rules/core/05-state-boundaries.mdc",
      ".ai/rules/core/06-utils-hooks.mdc",
      ".ai/rules/core/07-vue-auto-imports.mdc",
      ".ai/rules/core/08-vue-template-strictness.mdc",
      ".ai/rules/design-system/03-material-system.mdc",
      ".ai/rules/integrations/04-safe-storage.mdc",
      ".ai/rules/integrations/05-date-time.mdc",
      ".ai/rules/integrations/07-interaction-patterns.mdc",
      ".ai/rules/integrations/08-cross-platform-tauri.mdc",
      ".ai/rules/integrations/09-desktop-branch-governance.mdc"
    ],
    "src/adapters/**/*.ts": [".ai/rules/integrations/06-adapters-infra.mdc"],
    "src/api/**/*.ts": [
      ".ai/rules/integrations/00-network-routing-guardrails.mdc",
      ".ai/rules/integrations/01-http-alova.mdc"
    ],
    "src/App.vue": [".ai/rules/integrations/03-layout-architecture.mdc"],
    "src/components/**/*": [".ai/rules/core/02-ui-preflight.mdc"],
    "src/components/**/*.{vue,tsx}": [".ai/rules/components/00-primevue-ecosystem.mdc"],
    "src/components/**/*.vue": [
      ".ai/rules/components/01-primevue-pt-styling.mdc",
      ".ai/rules/components/03-echarts-theming.mdc"
    ],
    "src/components/ProForm/**": [".ai/rules/components/02-pro-components.mdc"],
    "src/components/ProTable/**": [".ai/rules/components/02-pro-components.mdc"],
    "src/components/UseEcharts/**/*.ts": [".ai/rules/components/03-echarts-theming.mdc"],
    "src/constants/**/*.ts": [".ai/rules/architecture/05-runtime-bootstrap.mdc"],
    "src/hooks/**/*.ts": [
      ".ai/rules/integrations/00-network-routing-guardrails.mdc",
      ".ai/rules/integrations/01-http-alova.mdc"
    ],
    "src/hooks/modules/**/*.ts": [".ai/rules/core/10-ai-generation-workflow.mdc"],
    "src/infra/**/*.ts": [
      ".ai/rules/integrations/00-network-routing-guardrails.mdc",
      ".ai/rules/integrations/06-adapters-infra.mdc"
    ],
    "src/layouts/**/*": [".ai/rules/core/02-ui-preflight.mdc"],
    "src/layouts/**/*.{vue,tsx}": [
      ".ai/rules/components/00-primevue-ecosystem.mdc",
      ".ai/rules/integrations/03-layout-architecture.mdc"
    ],
    "src/main.ts": [
      ".ai/rules/architecture/05-runtime-bootstrap.mdc",
      ".ai/rules/integrations/10-desktop-preflight.mdc"
    ],
    "src/router/**/*.ts": [
      ".ai/rules/integrations/00-network-routing-guardrails.mdc",
      ".ai/rules/integrations/02-router-rbac.mdc"
    ],
    "src/router/modules/**/*.ts": [".ai/rules/core/10-ai-generation-workflow.mdc"],
    "src/stores/**/*.ts": [
      ".ai/rules/architecture/04-store-organization.mdc",
      ".ai/rules/architecture/05-runtime-bootstrap.mdc",
      ".ai/rules/integrations/00-network-routing-guardrails.mdc"
    ],
    "src/types/**/*.ts": [".ai/rules/integrations/06-adapters-infra.mdc"],
    "src/utils/desktopWindow.ts": [".ai/rules/integrations/10-desktop-preflight.mdc"],
    "src/utils/env.ts": [".ai/rules/integrations/10-desktop-preflight.mdc"],
    "src/utils/theme/**/*.ts": [".ai/rules/architecture/05-runtime-bootstrap.mdc"],
    "src/views/**/*": [".ai/rules/core/02-ui-preflight.mdc"],
    "src/views/**/*.{vue,tsx,ts}": [".ai/rules/design-system/04-design-state-contract.mdc"],
    "src/views/**/*.{vue,tsx}": [".ai/rules/components/00-primevue-ecosystem.mdc"],
    "src/views/**/*.tsx": [".ai/rules/components/02-pro-components.mdc"],
    "src/views/**/*.vue": [
      ".ai/rules/components/01-primevue-pt-styling.mdc",
      ".ai/rules/components/02-pro-components.mdc",
      ".ai/rules/components/03-echarts-theming.mdc",
      ".ai/rules/core/10-ai-generation-workflow.mdc",
      ".ai/rules/integrations/00-network-routing-guardrails.mdc",
      ".ai/rules/integrations/01-http-alova.mdc",
      ".ai/rules/integrations/02-router-rbac.mdc"
    ],
    "test-results/**": [".ai/rules/integrations/09-desktop-branch-governance.mdc"]
  },
  "alwaysApply": [
    ".ai/rules/components/00-primevue-ecosystem.mdc",
    ".ai/rules/components/01-primevue-pt-styling.mdc",
    ".ai/rules/components/02-pro-components.mdc",
    ".ai/rules/components/03-echarts-theming.mdc",
    ".ai/rules/core/00-root-gatekeeper.mdc",
    ".ai/rules/core/01-global-preflight.mdc",
    ".ai/rules/core/02-ui-preflight.mdc",
    ".ai/rules/core/03-vue3-ts-architecture.mdc",
    ".ai/rules/core/06-utils-hooks.mdc",
    ".ai/rules/core/07-vue-auto-imports.mdc",
    ".ai/rules/core/08-vue-template-strictness.mdc",
    ".ai/rules/core/09-ai-anti-failure-guard.mdc",
    ".ai/rules/core/10-ai-generation-workflow.mdc",
    ".ai/rules/design-system/00-unocss-guardrails.mdc",
    ".ai/rules/design-system/02-size-density-system.mdc",
    ".ai/rules/design-system/03-material-system.mdc",
    ".ai/rules/design-system/04-design-state-contract.mdc",
    ".ai/rules/integrations/00-network-routing-guardrails.mdc",
    ".ai/rules/integrations/01-http-alova.mdc",
    ".ai/rules/integrations/02-router-rbac.mdc",
    ".ai/rules/integrations/03-layout-architecture.mdc",
    ".ai/rules/integrations/05-date-time.mdc",
    ".ai/rules/integrations/06-adapters-infra.mdc",
    ".ai/rules/integrations/07-interaction-patterns.mdc",
    ".ai/rules/integrations/10-desktop-preflight.mdc"
  ]
}
